[
  {
    "id": "DREAM_LUCID_FIRST",
    "title": "First Lucid Dream",
    "desc": "You took control and realized you were dreaming.",
    "category": "Dream",
    "secret": false,
    "unlocked": false,
    "date": null,
    "trigger": { "type": "DREAM_TAG", "value": "lucid" },
    "reward": { "xp": 50 }
  },
  {
    "id": "SHAME_PANTY_WHISPERER",
    "title": "Panty Whisperer",
    "desc": "Sniffed 10 pairs of panties. You're developing a refined taste.",
    "category": "Shame",
    "secret": false,
    "unlocked": false,
    "date": null,
    "trigger": { "type": "SHAME_COUNTER", "counter": "pantiesSniffed", "value": 10 },
    "reward": { "xp": 100, "title": "Panty Whisperer" }
  },
  {
    "id": "SHAME_SHAMEBOUND",
    "title": "Shamebound",
    "desc": "Confessed your first filthy act in the tracker. Welcome to the fold.",
    "category": "Shame",
    "secret": true,
    "unlocked": false,
    "date": null,
    "trigger": { "type": "CONFESSION_LOGGED", "value": 1 },
    "reward": { "xp": 200, "tokens": 5, "title": "Shamebound" }
  },
  {
    "id": "DUNGEON_BOSS_SLAYER",
    "title": "Boss Slayer",
    "desc": "Cleared your first Nightmare Dungeon. The darkness fears you.",
    "category": "Dungeon",
    "secret": false,
    "unlocked": false,
    "date": null,
    "trigger": { "type": "DUNGEON_CLEARED", "value": 1 },
    "reward": { "xp": 250 }
  },
  {
    "id": "COMPANION_DREAM_GUARDIAN",
    "title": "Dream Guardian",
    "desc": "Evolved a companion to their final form. A bond that transcends dreams.",
    "category": "Companion",
    "secret": false,
    "unlocked": false,
    "date": null,
    "trigger": { "type": "COMPANION_EVOLVED", "value": 1 },
    "reward": { "xp": 500, "title": "Dream Guardian" }
  },
  {
    "id": "RITUAL_OBEDIENCE_MASTER",
    "title": "Obedience Master",
    "desc": "Completed 25 obedience rituals. Your devotion is absolute.",
    "category": "Ritual",
    "secret": false,
    "unlocked": false,
    "date": null,
    "trigger": { "type": "RITUAL_COMPLETED", "value": 25 },
    "reward": { "xp": 300, "title": "Obedience Master" }
  },
  {
    "id": "SHAME_ULTIMATE_DEGRADATION",
    "title": "Ultimate Degradation",
    "desc": "Reached the highest tier of punishment. There is no redemption from this depth.",
    "category": "Shame",
    "secret": true,
    "unlocked": false,
    "date": null,
    "trigger": { "type": "PUNISHMENT_TIER_REACHED", "value": 5 },
    "reward": { "xp": 1000, "tokens": 50, "title": "Utterly Degraded" }
  },
  {
    "id": "MAP_VOYAGER",
    "title": "Multiverse Voyager",
    "desc": "Explored every known node on the Multiverse Map.",
    "category": "Map",
    "secret": false,
    "unlocked": false,
    "date": null,
    "trigger": { "type": "MAP_ALL_NODES_UNLOCKED" },
    "reward": { "xp": 1000, "title": "Multiverse Voyager" }
  },
  {
    "id": "MAP_PANTY_REALM_DISCOVERER",
    "title": "Panty Realm Discoverer",
    "desc": "Unlocked the fabled Panty Realm. A new world of lewd adventures awaits.",
    "category": "Map",
    "secret": true,
    "unlocked": false,
    "date": null,
    "trigger": { "type": "MAP_NODE_UNLOCKED", "value": "r2" },
    "reward": { "xp": 250, "tokens": 20 }
  },
  {
    "id": "DUNGEON_EXPLORER",
    "title": "Dungeon Explorer",
    "desc": "Completed your first dungeon run. The trials have only just begun.",
    "category": "Dungeon",
    "secret": false,
    "unlocked": false,
    "date": null,
    "trigger": { "type": "DUNGEON_CLEARED", "value": 1 },
    "reward": { "xp": 200, "tokens": 25 }
  },
  {
    "id": "DUNGEON_SHAME_MASTER",
    "title": "Master of Shame",
    "desc": "Cleared the Caves of Shame multiple times. You've embraced your darkest secrets.",
    "category": "Dungeon",
    "secret": false,
    "unlocked": false,
    "date": null,
    "trigger": { "type": "DUNGEON_CLEARED", "value": 3 },
    "reward": { "xp": 500, "tokens": 60 }
  },
  {
    "id": "DUNGEON_OBEDIENCE_ADEPT",
    "title": "Obedience Adept",
    "desc": "Mastered the Temple of Obedience. Your submission knows no bounds.",
    "category": "Dungeon",
    "secret": false,
    "unlocked": false,
    "date": null,
    "trigger": { "type": "DUNGEON_CLEARED", "value": 5 },
    "reward": { "xp": 750, "tokens": 80 }
  },
  {
    "id": "DUNGEON_DREAM_WALKER",
    "title": "Dream Walker",
    "desc": "Conquered the Labyrinth of Dreams. Reality bends to your will.",
    "category": "Dungeon",
    "secret": false,
    "unlocked": false,
    "date": null,
    "trigger": { "type": "DUNGEON_CLEARED", "value": 7 },
    "reward": { "xp": 1000, "tokens": 100 }
  },
  {
    "id": "DUNGEON_MASTER",
    "title": "Dungeon Master",
    "desc": "Cleared all available dungeons. You are the master of trials and tribulations.",
    "category": "Dungeon",
    "secret": false,
    "unlocked": false,
    "date": null,
    "trigger": { "type": "DUNGEON_CLEARED", "value": 10 },
    "reward": { "xp": 2000, "tokens": 200, "title": "Dungeon Master" }
  },
  {
    "id": "QUEST_DREAMGATE_EXPLORER",
    "title": "Dreamgate Explorer",
    "desc": "Found the mystical Dreamgate and stepped through to new realms of consciousness.",
    "category": "Dream",
    "secret": false,
    "unlocked": false,
    "date": null,
    "trigger": { "type": "QUEST_COMPLETED", "value": "q1" },
    "reward": { "xp": 100, "tokens": 25, "title": "Dream Explorer" }
  },
  {
    "id": "QUEST_BOUND_FEMBOY",
    "title": "Bound Femboy",
    "desc": "Completed 7 days of obedience training. Your submission has deepened significantly.",
    "category": "Ritual",
    "secret": false,
    "unlocked": false,
    "date": null,
    "trigger": { "type": "QUEST_COMPLETED", "value": "q2" },
    "reward": { "xp": 200, "tokens": 50, "title": "Bound Femboy" }
  },
  {
    "id": "QUEST_MASTER",
    "title": "Quest Master",
    "desc": "Completed 10 quests. Your dedication to growth is unmatched.",
    "category": "All",
    "secret": false,
    "unlocked": false,
    "date": null,
    "trigger": { "type": "QUESTS_COMPLETED", "value": 10 },
    "reward": { "xp": 500, "tokens": 100, "title": "Quest Master" }
  }
]
